Changelog.md
MANIFEST.in
README.md
VERSION
setup.py
isdc_geopanel/__init__.py
isdc_geopanel.egg-info/PKG-INFO
isdc_geopanel.egg-info/SOURCES.txt
isdc_geopanel.egg-info/dependency_links.txt
isdc_geopanel.egg-info/not-zip-safe
isdc_geopanel.egg-info/top_level.txt
isdc_geopanel/static/isdc_geopanel/js/immap.js
isdc_geopanel/static/isdc_geopanel/js/immap.panel.js
isdc_geopanel/templates/isdc_geopanel/panel.html