Metadata-Version: 1.0
Name: isdc-geopanel
Version: 1.0.1.dev0
Summary: panel module
Home-page: UNKNOWN
Author: iMMAP
Author-email: asdc@immap.org
License: iMMAP
Platform: UNKNOWN
